bemserver_grdf_adict_loader.py
bemserver_grdf_adict_loader-0.2.0.dist-info/entry_points.txt
bemserver_grdf_adict_loader-0.2.0.dist-info/LICENSE
bemserver_grdf_adict_loader-0.2.0.dist-info/WHEEL
bemserver_grdf_adict_loader-0.2.0.dist-info/METADATA
bemserver_grdf_adict_loader-0.2.0.dist-info/RECORD
